{
    "total_costs": {
        "total_fidelity_loss": 7.573416161467671,
        "epairs": 87,
        "execution_time": 1.2262561321258545,
        "num_comms": 70,
        "rgeo_mean_fid": 0.8961087705105362,
        "total_fidelity_log_sum": -7.905725644766684,
        "total_fidelity": 0.000368626860109353,
        "remote_hops": 53,
        "remote_swaps": 17,
        "cat_ents": 0,
        "local_fidelity_loss": 0.22702304496385223,
        "remote_fidelity_loss": 7.346393116503819,
        "local_fidelity_log_sum": -0.22718220464788746,
        "remote_fidelity_log_sum": -7.678543440118797,
        "local_fidelity": 0.796775592847106,
        "remote_fidelity": 0.0004626482831786354,
        "local_gate_num": 418
    },
    "num_records": 21,
    "records": [
        {
            "layer_start": 0,
            "layer_end": 3,
            "partition": [
                [
                    1,
                    3
                ],
                [
                    2,
                    0
                ],
                [
                    4,
                    5
                ],
                [
                    6,
                    7
                ]
            ],
            "mapping_type": "telegate",
            "costs": {
                "total_fidelity_loss": 0.011195556364600874,
                "epairs": 0,
                "execution_time": 0.0,
                "num_comms": 0,
                "rgeo_mean_fid": 1.0,
                "total_fidelity_log_sum": -0.011203662476441698,
                "total_fidelity": 0.9888588648205717,
                "remote_hops": 0,
                "remote_swaps": 0,
                "cat_ents": 0,
                "local_fidelity_loss": 0.011195556364600874,
                "remote_fidelity_loss": 0.0,
                "local_fidelity_log_sum": -0.011203662476441698,
                "remote_fidelity_log_sum": 0.0,
                "local_fidelity": 0.9888588648205717,
                "remote_fidelity": 1.0,
                "local_gate_num": 28
            },
            "logical_phy_map": {
                "1": [
                    0,
                    0
                ],
                "3": [
                    0,
                    1
                ],
                "2": [
                    1,
                    1
                ],
                "0": [
                    1,
                    0
                ],
                "4": [
                    2,
                    0
                ],
                "5": [
                    2,
                    1
                ],
                "6": [
                    3,
                    0
                ],
                "7": [
                    3,
                    1
                ]
            },
            "extra_info": null
        },
        {
            "layer_start": 4,
            "layer_end": 7,
            "partition": [
                [
                    1,
                    3
                ],
                [
                    2,
                    0
                ],
                [
                    4,
                    5
                ],
                [
                    6,
                    7
                ]
            ],
            "mapping_type": "telegate",
            "costs": {
                "total_fidelity_loss": 0.014865752666277267,
                "epairs": 0,
                "execution_time": 0.0,
                "num_comms": 0,
                "rgeo_mean_fid": 1.0,
                "total_fidelity_log_sum": -0.01487487711838192,
                "total_fidelity": 0.9852352073593098,
                "remote_hops": 0,
                "remote_swaps": 0,
                "cat_ents": 0,
                "local_fidelity_loss": 0.014865752666277267,
                "remote_fidelity_loss": 0.0,
                "local_fidelity_log_sum": -0.01487487711838192,
                "remote_fidelity_log_sum": 0.0,
                "local_fidelity": 0.9852352073593098,
                "remote_fidelity": 1.0,
                "local_gate_num": 24
            },
            "logical_phy_map": {
                "1": [
                    0,
                    0
                ],
                "3": [
                    0,
                    1
                ],
                "2": [
                    1,
                    1
                ],
                "0": [
                    1,
                    0
                ],
                "4": [
                    2,
                    0
                ],
                "5": [
                    2,
                    1
                ],
                "6": [
                    3,
                    0
                ],
                "7": [
                    3,
                    1
                ]
            },
            "extra_info": null
        },
        {
            "layer_start": 8,
            "layer_end": 11,
            "partition": [
                [
                    1,
                    3
                ],
                [
                    2,
                    0
                ],
                [
                    4,
                    5
                ],
                [
                    6,
                    7
                ]
            ],
            "mapping_type": "telegate",
            "costs": {
                "total_fidelity_loss": 0.011195556364600874,
                "epairs": 0,
                "execution_time": 0.0,
                "num_comms": 0,
                "rgeo_mean_fid": 1.0,
                "total_fidelity_log_sum": -0.011203662476441698,
                "total_fidelity": 0.988858864820572,
                "remote_hops": 0,
                "remote_swaps": 0,
                "cat_ents": 0,
                "local_fidelity_loss": 0.011195556364600874,
                "remote_fidelity_loss": 0.0,
                "local_fidelity_log_sum": -0.011203662476441698,
                "remote_fidelity_log_sum": 0.0,
                "local_fidelity": 0.988858864820572,
                "remote_fidelity": 1.0,
                "local_gate_num": 24
            },
            "logical_phy_map": {
                "1": [
                    0,
                    0
                ],
                "3": [
                    0,
                    1
                ],
                "2": [
                    1,
                    1
                ],
                "0": [
                    1,
                    0
                ],
                "4": [
                    2,
                    0
                ],
                "5": [
                    2,
                    1
                ],
                "6": [
                    3,
                    0
                ],
                "7": [
                    3,
                    1
                ]
            },
            "extra_info": null
        },
        {
            "layer_start": 12,
            "layer_end": 15,
            "partition": [
                [
                    1,
                    3
                ],
                [
                    2,
                    0
                ],
                [
                    4,
                    5
                ],
                [
                    6,
                    7
                ]
            ],
            "mapping_type": "telegate",
            "costs": {
                "total_fidelity_loss": 0.5180931701097904,
                "epairs": 6,
                "execution_time": 0.0,
                "num_comms": 6,
                "rgeo_mean_fid": 0.9140741340199604,
                "total_fidelity_log_sum": -0.5418150192983567,
                "total_fidelity": 0.5816915123417244,
                "remote_hops": 6,
                "remote_swaps": 0,
                "cat_ents": 0,
                "local_fidelity_loss": 0.0027526472262572963,
                "remote_fidelity_loss": 0.515340522883533,
                "local_fidelity_log_sum": -0.002753410981455167,
                "remote_fidelity_log_sum": -0.5390616083169015,
                "local_fidelity": 0.9972503761778951,
                "remote_fidelity": 0.5832953551455557,
                "local_gate_num": 13
            },
            "logical_phy_map": {
                "1": [
                    0,
                    0
                ],
                "3": [
                    0,
                    1
                ],
                "2": [
                    1,
                    1
                ],
                "0": [
                    1,
                    0
                ],
                "4": [
                    2,
                    0
                ],
                "5": [
                    2,
                    1
                ],
                "6": [
                    3,
                    0
                ],
                "7": [
                    3,
                    1
                ]
            },
            "extra_info": null
        },
        {
            "layer_start": 16,
            "layer_end": 19,
            "partition": [
                [
                    1,
                    7
                ],
                [
                    3,
                    4
                ],
                [
                    2,
                    0
                ],
                [
                    6,
                    5
                ]
            ],
            "mapping_type": "telegate",
            "costs": {
                "total_fidelity_loss": 0.6801565189946777,
                "epairs": 8,
                "execution_time": 0.0,
                "num_comms": 7,
                "rgeo_mean_fid": 0.9053775035803988,
                "total_fidelity_log_sum": -0.7098751213369593,
                "total_fidelity": 0.4917055971647124,
                "remote_hops": 6,
                "remote_swaps": 1,
                "cat_ents": 0,
                "local_fidelity_loss": 0.014040687320644016,
                "remote_fidelity_loss": 0.6661158316740337,
                "local_fidelity_log_sum": -0.014052082733207379,
                "remote_fidelity_log_sum": -0.6958230386037519,
                "local_fidelity": 0.986046186944974,
                "remote_fidelity": 0.4986638594365883,
                "local_gate_num": 15
            },
            "logical_phy_map": {
                "1": [
                    0,
                    0
                ],
                "3": [
                    1,
                    0
                ],
                "2": [
                    2,
                    0
                ],
                "0": [
                    2,
                    1
                ],
                "4": [
                    1,
                    1
                ],
                "5": [
                    3,
                    1
                ],
                "6": [
                    3,
                    0
                ],
                "7": [
                    0,
                    1
                ]
            },
            "extra_info": null
        },
        {
            "layer_start": 20,
            "layer_end": 23,
            "partition": [
                [
                    1,
                    7
                ],
                [
                    3,
                    5
                ],
                [
                    4,
                    2
                ],
                [
                    6,
                    0
                ]
            ],
            "mapping_type": "telegate",
            "costs": {
                "total_fidelity_loss": 0.334491489551046,
                "epairs": 4,
                "execution_time": 0.0,
                "num_comms": 4,
                "rgeo_mean_fid": 0.9186866935513825,
                "total_fidelity_log_sum": -0.348561093746755,
                "total_fidelity": 0.7057027996787747,
                "remote_hops": 4,
                "remote_swaps": 0,
                "cat_ents": 0,
                "local_fidelity_loss": 0.009314216348869756,
                "remote_fidelity_loss": 0.32517727320217626,
                "local_fidelity_log_sum": -0.00932055051781633,
                "remote_fidelity_log_sum": -0.33924054322893865,
                "local_fidelity": 0.9907227511768562,
                "remote_fidelity": 0.7123110868711625,
                "local_gate_num": 20
            },
            "logical_phy_map": {
                "1": [
                    0,
                    0
                ],
                "3": [
                    1,
                    0
                ],
                "2": [
                    2,
                    0
                ],
                "0": [
                    3,
                    1
                ],
                "4": [
                    2,
                    1
                ],
                "5": [
                    1,
                    1
                ],
                "6": [
                    3,
                    0
                ],
                "7": [
                    0,
                    1
                ]
            },
            "extra_info": null
        },
        {
            "layer_start": 24,
            "layer_end": 27,
            "partition": [
                [
                    1,
                    7
                ],
                [
                    3,
                    5
                ],
                [
                    4,
                    2
                ],
                [
                    6,
                    0
                ]
            ],
            "mapping_type": "telegate",
            "costs": {
                "total_fidelity_loss": 0.010231765424288854,
                "epairs": 0,
                "execution_time": 0.0,
                "num_comms": 0,
                "rgeo_mean_fid": 1.0,
                "total_fidelity_log_sum": -0.010238354178301386,
                "total_fidelity": 0.9898138793560423,
                "remote_hops": 0,
                "remote_swaps": 0,
                "cat_ents": 0,
                "local_fidelity_loss": 0.010231765424288854,
                "remote_fidelity_loss": 0.0,
                "local_fidelity_log_sum": -0.010238354178301386,
                "remote_fidelity_log_sum": 0.0,
                "local_fidelity": 0.9898138793560423,
                "remote_fidelity": 1.0,
                "local_gate_num": 17
            },
            "logical_phy_map": {
                "1": [
                    0,
                    0
                ],
                "3": [
                    1,
                    0
                ],
                "2": [
                    2,
                    0
                ],
                "0": [
                    3,
                    1
                ],
                "4": [
                    2,
                    1
                ],
                "5": [
                    1,
                    1
                ],
                "6": [
                    3,
                    0
                ],
                "7": [
                    0,
                    1
                ]
            },
            "extra_info": null
        },
        {
            "layer_start": 28,
            "layer_end": 31,
            "partition": [
                [
                    1,
                    7
                ],
                [
                    3,
                    5
                ],
                [
                    4,
                    2
                ],
                [
                    6,
                    0
                ]
            ],
            "mapping_type": "telegate",
            "costs": {
                "total_fidelity_loss": 0.008396667273450656,
                "epairs": 0,
                "execution_time": 0.0,
                "num_comms": 0,
                "rgeo_mean_fid": 1.0,
                "total_fidelity_log_sum": -0.008402746857331275,
                "total_fidelity": 0.9916324575464716,
                "remote_hops": 0,
                "remote_swaps": 0,
                "cat_ents": 0,
                "local_fidelity_loss": 0.008396667273450656,
                "remote_fidelity_loss": 0.0,
                "local_fidelity_log_sum": -0.008402746857331275,
                "remote_fidelity_log_sum": 0.0,
                "local_fidelity": 0.9916324575464716,
                "remote_fidelity": 1.0,
                "local_gate_num": 18
            },
            "logical_phy_map": {
                "1": [
                    0,
                    0
                ],
                "3": [
                    1,
                    0
                ],
                "2": [
                    2,
                    0
                ],
                "0": [
                    3,
                    1
                ],
                "4": [
                    2,
                    1
                ],
                "5": [
                    1,
                    1
                ],
                "6": [
                    3,
                    0
                ],
                "7": [
                    0,
                    1
                ]
            },
            "extra_info": null
        },
        {
            "layer_start": 32,
            "layer_end": 35,
            "partition": [
                [
                    4,
                    3
                ],
                [
                    6,
                    1
                ],
                [
                    5,
                    0
                ],
                [
                    7,
                    2
                ]
            ],
            "mapping_type": "telegate",
            "costs": {
                "total_fidelity_loss": 1.0456392821631293,
                "epairs": 12,
                "execution_time": 0.0,
                "num_comms": 10,
                "rgeo_mean_fid": 0.8977960774942653,
                "total_fidelity_log_sum": -1.0930931030274953,
                "total_fidelity": 0.33517814813491675,
                "remote_hops": 8,
                "remote_swaps": 2,
                "cat_ents": 0,
                "local_fidelity_loss": 0.014958236396063114,
                "remote_fidelity_loss": 1.030681045767066,
                "local_fidelity_log_sum": -0.014969886393692435,
                "remote_fidelity_log_sum": -1.0781232166338028,
                "local_fidelity": 0.9851416053228497,
                "remote_fidelity": 0.34023347133437987,
                "local_gate_num": 20
            },
            "logical_phy_map": {
                "1": [
                    1,
                    0
                ],
                "3": [
                    0,
                    0
                ],
                "2": [
                    3,
                    1
                ],
                "0": [
                    2,
                    0
                ],
                "4": [
                    0,
                    1
                ],
                "5": [
                    2,
                    1
                ],
                "6": [
                    1,
                    1
                ],
                "7": [
                    3,
                    0
                ]
            },
            "extra_info": null
        },
        {
            "layer_start": 36,
            "layer_end": 39,
            "partition": [
                [
                    4,
                    3
                ],
                [
                    6,
                    1
                ],
                [
                    5,
                    0
                ],
                [
                    7,
                    2
                ]
            ],
            "mapping_type": "telegate",
            "costs": {
                "total_fidelity_loss": 0.015875785471482214,
                "epairs": 0,
                "execution_time": 0.0,
                "num_comms": 0,
                "rgeo_mean_fid": 1.0,
                "total_fidelity_log_sum": -0.01588769005417749,
                "total_fidelity": 0.9842378535481721,
                "remote_hops": 0,
                "remote_swaps": 0,
                "cat_ents": 0,
                "local_fidelity_loss": 0.015875785471482214,
                "remote_fidelity_loss": 0.0,
                "local_fidelity_log_sum": -0.01588769005417749,
                "remote_fidelity_log_sum": 0.0,
                "local_fidelity": 0.9842378535481721,
                "remote_fidelity": 1.0,
                "local_gate_num": 22
            },
            "logical_phy_map": {
                "1": [
                    1,
                    0
                ],
                "3": [
                    0,
                    0
                ],
                "2": [
                    3,
                    1
                ],
                "0": [
                    2,
                    0
                ],
                "4": [
                    0,
                    1
                ],
                "5": [
                    2,
                    1
                ],
                "6": [
                    1,
                    1
                ],
                "7": [
                    3,
                    0
                ]
            },
            "extra_info": null
        },
        {
            "layer_start": 40,
            "layer_end": 43,
            "partition": [
                [
                    1,
                    5
                ],
                [
                    2,
                    4
                ],
                [
                    3,
                    7
                ],
                [
                    6,
                    0
                ]
            ],
            "mapping_type": "telegate",
            "costs": {
                "total_fidelity_loss": 1.3679714244092622,
                "epairs": 16,
                "execution_time": 0.0,
                "num_comms": 8,
                "rgeo_mean_fid": 0.8376369803897552,
                "total_fidelity_log_sum": -1.4294852259996682,
                "total_fidelity": 0.23943214396792187,
                "remote_hops": 0,
                "remote_swaps": 8,
                "cat_ents": 0,
                "local_fidelity_loss": 0.012113105440019973,
                "remote_fidelity_loss": 1.3558583189692424,
                "local_fidelity_log_sum": -0.012121466136926754,
                "remote_fidelity_log_sum": -1.4173637598627415,
                "local_fidelity": 0.9879517028966834,
                "remote_fidelity": 0.24235207375614073,
                "local_gate_num": 24
            },
            "logical_phy_map": {
                "1": [
                    0,
                    1
                ],
                "3": [
                    2,
                    1
                ],
                "2": [
                    1,
                    1
                ],
                "0": [
                    3,
                    0
                ],
                "4": [
                    1,
                    0
                ],
                "5": [
                    0,
                    0
                ],
                "6": [
                    3,
                    1
                ],
                "7": [
                    2,
                    0
                ]
            },
            "extra_info": null
        },
        {
            "layer_start": 44,
            "layer_end": 47,
            "partition": [
                [
                    1,
                    5
                ],
                [
                    2,
                    4
                ],
                [
                    3,
                    7
                ],
                [
                    6,
                    0
                ]
            ],
            "mapping_type": "telegate",
            "costs": {
                "total_fidelity_loss": 0.013030654515439073,
                "epairs": 0,
                "execution_time": 0.0,
                "num_comms": 0,
                "rgeo_mean_fid": 1.0,
                "total_fidelity_log_sum": -0.01303926979741181,
                "total_fidelity": 0.9870453731873665,
                "remote_hops": 0,
                "remote_swaps": 0,
                "cat_ents": 0,
                "local_fidelity_loss": 0.013030654515439073,
                "remote_fidelity_loss": 0.0,
                "local_fidelity_log_sum": -0.01303926979741181,
                "remote_fidelity_log_sum": 0.0,
                "local_fidelity": 0.9870453731873665,
                "remote_fidelity": 1.0,
                "local_gate_num": 22
            },
            "logical_phy_map": {
                "1": [
                    0,
                    1
                ],
                "3": [
                    2,
                    1
                ],
                "2": [
                    1,
                    1
                ],
                "0": [
                    3,
                    0
                ],
                "4": [
                    1,
                    0
                ],
                "5": [
                    0,
                    0
                ],
                "6": [
                    3,
                    1
                ],
                "7": [
                    2,
                    0
                ]
            },
            "extra_info": null
        },
        {
            "layer_start": 48,
            "layer_end": 51,
            "partition": [
                [
                    1,
                    5
                ],
                [
                    2,
                    4
                ],
                [
                    3,
                    7
                ],
                [
                    6,
                    0
                ]
            ],
            "mapping_type": "telegate",
            "costs": {
                "total_fidelity_loss": 0.011195556364600874,
                "epairs": 0,
                "execution_time": 0.0,
                "num_comms": 0,
                "rgeo_mean_fid": 1.0,
                "total_fidelity_log_sum": -0.011203662476441698,
                "total_fidelity": 0.988858864820572,
                "remote_hops": 0,
                "remote_swaps": 0,
                "cat_ents": 0,
                "local_fidelity_loss": 0.011195556364600874,
                "remote_fidelity_loss": 0.0,
                "local_fidelity_log_sum": -0.011203662476441698,
                "remote_fidelity_log_sum": 0.0,
                "local_fidelity": 0.988858864820572,
                "remote_fidelity": 1.0,
                "local_gate_num": 24
            },
            "logical_phy_map": {
                "1": [
                    0,
                    1
                ],
                "3": [
                    2,
                    1
                ],
                "2": [
                    1,
                    1
                ],
                "0": [
                    3,
                    0
                ],
                "4": [
                    1,
                    0
                ],
                "5": [
                    0,
                    0
                ],
                "6": [
                    3,
                    1
                ],
                "7": [
                    2,
                    0
                ]
            },
            "extra_info": null
        },
        {
            "layer_start": 52,
            "layer_end": 55,
            "partition": [
                [
                    6,
                    5
                ],
                [
                    2,
                    0
                ],
                [
                    4,
                    3
                ],
                [
                    7,
                    1
                ]
            ],
            "mapping_type": "telegate",
            "costs": {
                "total_fidelity_loss": 1.1806533056839488,
                "epairs": 14,
                "execution_time": 0.0,
                "num_comms": 9,
                "rgeo_mean_fid": 0.873469102900389,
                "total_fidelity_log_sum": -1.2325125811684714,
                "total_fidelity": 0.29155909071314495,
                "remote_hops": 4,
                "remote_swaps": 5,
                "cat_ents": 0,
                "local_fidelity_loss": 0.014958236396063114,
                "remote_fidelity_loss": 1.1656950692878856,
                "local_fidelity_log_sum": -0.014969886393692435,
                "remote_fidelity_log_sum": -1.217542694774779,
                "local_fidelity": 0.9851416053228496,
                "remote_fidelity": 0.2959565296377829,
                "local_gate_num": 20
            },
            "logical_phy_map": {
                "1": [
                    3,
                    1
                ],
                "3": [
                    2,
                    1
                ],
                "2": [
                    1,
                    1
                ],
                "0": [
                    1,
                    0
                ],
                "4": [
                    2,
                    0
                ],
                "5": [
                    0,
                    0
                ],
                "6": [
                    0,
                    1
                ],
                "7": [
                    3,
                    0
                ]
            },
            "extra_info": null
        },
        {
            "layer_start": 56,
            "layer_end": 59,
            "partition": [
                [
                    6,
                    5
                ],
                [
                    2,
                    0
                ],
                [
                    4,
                    3
                ],
                [
                    7,
                    1
                ]
            ],
            "mapping_type": "telegate",
            "costs": {
                "total_fidelity_loss": 0.015875785471482214,
                "epairs": 0,
                "execution_time": 0.0,
                "num_comms": 0,
                "rgeo_mean_fid": 1.0,
                "total_fidelity_log_sum": -0.01588769005417749,
                "total_fidelity": 0.9842378535481723,
                "remote_hops": 0,
                "remote_swaps": 0,
                "cat_ents": 0,
                "local_fidelity_loss": 0.015875785471482214,
                "remote_fidelity_loss": 0.0,
                "local_fidelity_log_sum": -0.01588769005417749,
                "remote_fidelity_log_sum": 0.0,
                "local_fidelity": 0.9842378535481723,
                "remote_fidelity": 1.0,
                "local_gate_num": 22
            },
            "logical_phy_map": {
                "1": [
                    3,
                    1
                ],
                "3": [
                    2,
                    1
                ],
                "2": [
                    1,
                    1
                ],
                "0": [
                    1,
                    0
                ],
                "4": [
                    2,
                    0
                ],
                "5": [
                    0,
                    0
                ],
                "6": [
                    0,
                    1
                ],
                "7": [
                    3,
                    0
                ]
            },
            "extra_info": null
        },
        {
            "layer_start": 60,
            "layer_end": 63,
            "partition": [
                [
                    6,
                    5
                ],
                [
                    2,
                    0
                ],
                [
                    4,
                    3
                ],
                [
                    7,
                    1
                ]
            ],
            "mapping_type": "telegate",
            "costs": {
                "total_fidelity_loss": 0.5190107191852095,
                "epairs": 6,
                "execution_time": 0.0,
                "num_comms": 6,
                "rgeo_mean_fid": 0.9140741340199604,
                "total_fidelity_log_sum": -0.5427328229588417,
                "total_fidelity": 0.5811578786653542,
                "remote_hops": 6,
                "remote_swaps": 0,
                "cat_ents": 0,
                "local_fidelity_loss": 0.0036701963016763954,
                "remote_fidelity_loss": 0.515340522883533,
                "local_fidelity_log_sum": -0.0036712146419402227,
                "remote_fidelity_log_sum": -0.5390616083169015,
                "local_fidelity": 0.9963355160274368,
                "remote_fidelity": 0.5832953551455556,
                "local_gate_num": 18
            },
            "logical_phy_map": {
                "1": [
                    3,
                    1
                ],
                "3": [
                    2,
                    1
                ],
                "2": [
                    1,
                    1
                ],
                "0": [
                    1,
                    0
                ],
                "4": [
                    2,
                    0
                ],
                "5": [
                    0,
                    0
                ],
                "6": [
                    0,
                    1
                ],
                "7": [
                    3,
                    0
                ]
            },
            "extra_info": null
        },
        {
            "layer_start": 64,
            "layer_end": 67,
            "partition": [
                [
                    6,
                    5
                ],
                [
                    2,
                    0
                ],
                [
                    4,
                    3
                ],
                [
                    7,
                    1
                ]
            ],
            "mapping_type": "telegate",
            "costs": {
                "total_fidelity_loss": 0.5190107191852095,
                "epairs": 6,
                "execution_time": 0.0,
                "num_comms": 6,
                "rgeo_mean_fid": 0.9140741340199604,
                "total_fidelity_log_sum": -0.5427328229588417,
                "total_fidelity": 0.5811578786653542,
                "remote_hops": 6,
                "remote_swaps": 0,
                "cat_ents": 0,
                "local_fidelity_loss": 0.0036701963016763954,
                "remote_fidelity_loss": 0.515340522883533,
                "local_fidelity_log_sum": -0.0036712146419402227,
                "remote_fidelity_log_sum": -0.5390616083169015,
                "local_fidelity": 0.9963355160274368,
                "remote_fidelity": 0.5832953551455556,
                "local_gate_num": 12
            },
            "logical_phy_map": {
                "1": [
                    3,
                    1
                ],
                "3": [
                    2,
                    1
                ],
                "2": [
                    1,
                    1
                ],
                "0": [
                    1,
                    0
                ],
                "4": [
                    2,
                    0
                ],
                "5": [
                    0,
                    0
                ],
                "6": [
                    0,
                    1
                ],
                "7": [
                    3,
                    0
                ]
            },
            "extra_info": null
        },
        {
            "layer_start": 68,
            "layer_end": 71,
            "partition": [
                [
                    1,
                    6
                ],
                [
                    0,
                    5
                ],
                [
                    2,
                    3
                ],
                [
                    4,
                    7
                ]
            ],
            "mapping_type": "telegate",
            "costs": {
                "total_fidelity_loss": 0.5987052915170711,
                "epairs": 7,
                "execution_time": 0.0,
                "num_comms": 7,
                "rgeo_mean_fid": 0.9155722071046734,
                "total_fidelity_log_sum": -0.625425324707737,
                "total_fidelity": 0.5350338170161717,
                "remote_hops": 7,
                "remote_swaps": 0,
                "cat_ents": 0,
                "local_fidelity_loss": 0.00797711423828774,
                "remote_fidelity_loss": 0.5907281772787834,
                "local_fidelity_log_sum": -0.007983001247410332,
                "remote_fidelity_log_sum": -0.6174423234603267,
                "local_fidelity": 0.9920487782854703,
                "remote_fidelity": 0.5393220865014878,
                "local_gate_num": 18
            },
            "logical_phy_map": {
                "1": [
                    0,
                    0
                ],
                "3": [
                    2,
                    1
                ],
                "2": [
                    2,
                    0
                ],
                "0": [
                    1,
                    0
                ],
                "4": [
                    3,
                    1
                ],
                "5": [
                    1,
                    1
                ],
                "6": [
                    0,
                    1
                ],
                "7": [
                    3,
                    0
                ]
            },
            "extra_info": null
        },
        {
            "layer_start": 72,
            "layer_end": 75,
            "partition": [
                [
                    1,
                    5
                ],
                [
                    2,
                    3
                ],
                [
                    4,
                    0
                ],
                [
                    6,
                    7
                ]
            ],
            "mapping_type": "telegate",
            "costs": {
                "total_fidelity_loss": 0.6819916171455158,
                "epairs": 8,
                "execution_time": 0.0,
                "num_comms": 7,
                "rgeo_mean_fid": 0.9053775035803988,
                "total_fidelity_log_sum": -0.7117107286579294,
                "total_fidelity": 0.49080384665391513,
                "remote_hops": 6,
                "remote_swaps": 1,
                "cat_ents": 0,
                "local_fidelity_loss": 0.01587578547148221,
                "remote_fidelity_loss": 0.6661158316740337,
                "local_fidelity_log_sum": -0.01588769005417749,
                "remote_fidelity_log_sum": -0.6958230386037519,
                "local_fidelity": 0.9842378535481722,
                "remote_fidelity": 0.4986638594365883,
                "local_gate_num": 22
            },
            "logical_phy_map": {
                "1": [
                    0,
                    0
                ],
                "3": [
                    1,
                    1
                ],
                "2": [
                    1,
                    0
                ],
                "0": [
                    2,
                    0
                ],
                "4": [
                    2,
                    1
                ],
                "5": [
                    0,
                    1
                ],
                "6": [
                    3,
                    1
                ],
                "7": [
                    3,
                    0
                ]
            },
            "extra_info": null
        },
        {
            "layer_start": 76,
            "layer_end": 79,
            "partition": [
                [
                    1,
                    5
                ],
                [
                    2,
                    3
                ],
                [
                    4,
                    0
                ],
                [
                    6,
                    7
                ]
            ],
            "mapping_type": "telegate",
            "costs": {
                "total_fidelity_loss": 0.01441399849091401,
                "epairs": 0,
                "execution_time": 0.0,
                "num_comms": 0,
                "rgeo_mean_fid": 1.0,
                "total_fidelity_log_sum": -0.014424323705473063,
                "total_fidelity": 0.9856792084600979,
                "remote_hops": 0,
                "remote_swaps": 0,
                "cat_ents": 0,
                "local_fidelity_loss": 0.01441399849091401,
                "remote_fidelity_loss": 0.0,
                "local_fidelity_log_sum": -0.014424323705473063,
                "remote_fidelity_log_sum": 0.0,
                "local_fidelity": 0.9856792084600979,
                "remote_fidelity": 1.0,
                "local_gate_num": 23
            },
            "logical_phy_map": {
                "1": [
                    0,
                    0
                ],
                "3": [
                    1,
                    1
                ],
                "2": [
                    1,
                    0
                ],
                "0": [
                    2,
                    0
                ],
                "4": [
                    2,
                    1
                ],
                "5": [
                    0,
                    1
                ],
                "6": [
                    3,
                    1
                ],
                "7": [
                    3,
                    0
                ]
            },
            "extra_info": null
        },
        {
            "layer_start": 80,
            "layer_end": 82,
            "partition": [
                [
                    1,
                    5
                ],
                [
                    2,
                    3
                ],
                [
                    4,
                    0
                ],
                [
                    6,
                    7
                ]
            ],
            "mapping_type": "telegate",
            "costs": {
                "total_fidelity_loss": 0.001415545115675281,
                "epairs": 0,
                "execution_time": 0.0,
                "num_comms": 0,
                "rgeo_mean_fid": 1.0,
                "total_fidelity_log_sum": -0.0014158617110491697,
                "total_fidelity": 0.9985851401482561,
                "remote_hops": 0,
                "remote_swaps": 0,
                "cat_ents": 0,
                "local_fidelity_loss": 0.001415545115675281,
                "remote_fidelity_loss": 0.0,
                "local_fidelity_log_sum": -0.0014158617110491697,
                "remote_fidelity_log_sum": 0.0,
                "local_fidelity": 0.9985851401482561,
                "remote_fidelity": 1.0,
                "local_gate_num": 12
            },
            "logical_phy_map": {
                "1": [
                    0,
                    0
                ],
                "3": [
                    1,
                    1
                ],
                "2": [
                    1,
                    0
                ],
                "0": [
                    2,
                    0
                ],
                "4": [
                    2,
                    1
                ],
                "5": [
                    0,
                    1
                ],
                "6": [
                    3,
                    1
                ],
                "7": [
                    3,
                    0
                ]
            },
            "extra_info": null
        }
    ]
}