{
    "total_costs": {
        "num_comms": 13,
        "epairs": 23,
        "total_fidelity_loss": 1.0787324299427747,
        "rgeo_mean_fid": 0.93,
        "execution_time": 0.5935037136077881,
        "total_fidelity_log_sum": -1.1125757547661594,
        "total_fidelity": 0.3287111903039831,
        "remote_hops": 3,
        "remote_swaps": 10,
        "local_fidelity_loss": 0.1687324299427753,
        "remote_fidelity_loss": 0.9099999999999994,
        "local_fidelity_log_sum": -0.16915674791329943,
        "remote_fidelity_log_sum": -0.9434190068528601,
        "local_fidelity": 0.844376538751876,
        "remote_fidelity": 0.3892945566558149,
        "local_gate_num": 145
    },
    "num_records": 33,
    "records": [
        {
            "layer_start": 0,
            "layer_end": 0,
            "partition": [
                [
                    0,
                    1,
                    2
                ],
                [
                    3
                ]
            ],
            "mapping_type": "telegate",
            "costs": {
                "num_comms": 0,
                "epairs": 0,
                "total_fidelity_loss": 0.0,
                "rgeo_mean_fid": 1.0,
                "execution_time": 0.0,
                "total_fidelity_log_sum": 0.0,
                "total_fidelity": 1.0,
                "remote_hops": 0,
                "remote_swaps": 0,
                "local_fidelity_loss": 0.0,
                "remote_fidelity_loss": 0.0,
                "local_fidelity_log_sum": 0.0,
                "remote_fidelity_log_sum": 0.0,
                "local_fidelity": 1.0,
                "remote_fidelity": 1.0,
                "local_gate_num": 4
            },
            "logical_phy_map": {
                "0": [
                    0,
                    1
                ],
                "1": [
                    0,
                    2
                ],
                "2": [
                    0,
                    0
                ],
                "3": [
                    1,
                    null
                ]
            },
            "extra_info": null
        },
        {
            "layer_start": 1,
            "layer_end": 1,
            "partition": [
                [
                    0,
                    1,
                    2
                ],
                [
                    3
                ]
            ],
            "mapping_type": "telegate",
            "costs": {
                "num_comms": 0,
                "epairs": 0,
                "total_fidelity_loss": 0.0009490785341005846,
                "rgeo_mean_fid": 1.0,
                "execution_time": 0.0,
                "total_fidelity_log_sum": -0.000949198851153123,
                "total_fidelity": 0.9990512514955755,
                "remote_hops": 0,
                "remote_swaps": 0,
                "local_fidelity_loss": 0.0009490785341005846,
                "remote_fidelity_loss": 0.0,
                "local_fidelity_log_sum": -0.000949198851153123,
                "remote_fidelity_log_sum": 0.0,
                "local_fidelity": 0.9990512514955755,
                "remote_fidelity": 1.0,
                "local_gate_num": 4
            },
            "logical_phy_map": {
                "0": [
                    0,
                    1
                ],
                "1": [
                    0,
                    2
                ],
                "2": [
                    0,
                    0
                ],
                "3": [
                    1,
                    null
                ]
            },
            "extra_info": null
        },
        {
            "layer_start": 2,
            "layer_end": 2,
            "partition": [
                [
                    0,
                    1,
                    2
                ],
                [
                    3
                ]
            ],
            "mapping_type": "telegate",
            "costs": {
                "num_comms": 0,
                "epairs": 0,
                "total_fidelity_loss": 0.0,
                "rgeo_mean_fid": 1.0,
                "execution_time": 0.0,
                "total_fidelity_log_sum": 0.0,
                "total_fidelity": 1.0,
                "remote_hops": 0,
                "remote_swaps": 0,
                "local_fidelity_loss": 0.0,
                "remote_fidelity_loss": 0.0,
                "local_fidelity_log_sum": 0.0,
                "remote_fidelity_log_sum": 0.0,
                "local_fidelity": 1.0,
                "remote_fidelity": 1.0,
                "local_gate_num": 4
            },
            "logical_phy_map": {
                "0": [
                    0,
                    1
                ],
                "1": [
                    0,
                    2
                ],
                "2": [
                    0,
                    0
                ],
                "3": [
                    1,
                    null
                ]
            },
            "extra_info": null
        },
        {
            "layer_start": 3,
            "layer_end": 3,
            "partition": [
                [
                    0,
                    1,
                    2
                ],
                [
                    3
                ]
            ],
            "mapping_type": "telegate",
            "costs": {
                "num_comms": 1,
                "epairs": 1,
                "total_fidelity_loss": 0.07228652841594507,
                "rgeo_mean_fid": 0.93,
                "execution_time": 0.0,
                "total_fidelity_log_sum": -0.07485983934854362,
                "total_fidelity": 0.9278735285731711,
                "remote_hops": 1,
                "remote_swaps": 0,
                "local_fidelity_loss": 0.002286528415945122,
                "remote_fidelity_loss": 0.06999999999999995,
                "local_fidelity_log_sum": -0.0022891465137082428,
                "remote_fidelity_log_sum": -0.07257069283483537,
                "local_fidelity": 0.9977134715840549,
                "remote_fidelity": 0.93,
                "local_gate_num": 1
            },
            "logical_phy_map": {
                "0": [
                    0,
                    1
                ],
                "1": [
                    0,
                    2
                ],
                "2": [
                    0,
                    0
                ],
                "3": [
                    1,
                    null
                ]
            },
            "extra_info": null
        },
        {
            "layer_start": 4,
            "layer_end": 4,
            "partition": [
                [
                    0,
                    1,
                    2
                ],
                [
                    3
                ]
            ],
            "mapping_type": "telegate",
            "costs": {
                "num_comms": 0,
                "epairs": 0,
                "total_fidelity_loss": 0.0009490785341005846,
                "rgeo_mean_fid": 1.0,
                "execution_time": 0.0,
                "total_fidelity_log_sum": -0.000949198851153123,
                "total_fidelity": 0.9990512514955755,
                "remote_hops": 0,
                "remote_swaps": 0,
                "local_fidelity_loss": 0.0009490785341005846,
                "remote_fidelity_loss": 0.0,
                "local_fidelity_log_sum": -0.000949198851153123,
                "remote_fidelity_log_sum": 0.0,
                "local_fidelity": 0.9990512514955755,
                "remote_fidelity": 1.0,
                "local_gate_num": 4
            },
            "logical_phy_map": {
                "0": [
                    0,
                    1
                ],
                "1": [
                    0,
                    2
                ],
                "2": [
                    0,
                    0
                ],
                "3": [
                    1,
                    null
                ]
            },
            "extra_info": null
        },
        {
            "layer_start": 5,
            "layer_end": 5,
            "partition": [
                [
                    0,
                    1,
                    2
                ],
                [
                    3
                ]
            ],
            "mapping_type": "telegate",
            "costs": {
                "num_comms": 0,
                "epairs": 0,
                "total_fidelity_loss": 0.0,
                "rgeo_mean_fid": 1.0,
                "execution_time": 0.0,
                "total_fidelity_log_sum": 0.0,
                "total_fidelity": 1.0,
                "remote_hops": 0,
                "remote_swaps": 0,
                "local_fidelity_loss": 0.0,
                "remote_fidelity_loss": 0.0,
                "local_fidelity_log_sum": 0.0,
                "remote_fidelity_log_sum": 0.0,
                "local_fidelity": 1.0,
                "remote_fidelity": 1.0,
                "local_gate_num": 2
            },
            "logical_phy_map": {
                "0": [
                    0,
                    1
                ],
                "1": [
                    0,
                    2
                ],
                "2": [
                    0,
                    0
                ],
                "3": [
                    1,
                    null
                ]
            },
            "extra_info": null
        },
        {
            "layer_start": 6,
            "layer_end": 6,
            "partition": [
                [
                    0,
                    1,
                    2
                ],
                [
                    3
                ]
            ],
            "mapping_type": "telegate",
            "costs": {
                "num_comms": 1,
                "epairs": 1,
                "total_fidelity_loss": 0.07228652841594507,
                "rgeo_mean_fid": 0.93,
                "execution_time": 0.0,
                "total_fidelity_log_sum": -0.07485983934854362,
                "total_fidelity": 0.9278735285731711,
                "remote_hops": 1,
                "remote_swaps": 0,
                "local_fidelity_loss": 0.002286528415945122,
                "remote_fidelity_loss": 0.06999999999999995,
                "local_fidelity_log_sum": -0.0022891465137082428,
                "remote_fidelity_log_sum": -0.07257069283483537,
                "local_fidelity": 0.9977134715840549,
                "remote_fidelity": 0.93,
                "local_gate_num": 1
            },
            "logical_phy_map": {
                "0": [
                    0,
                    1
                ],
                "1": [
                    0,
                    2
                ],
                "2": [
                    0,
                    0
                ],
                "3": [
                    1,
                    null
                ]
            },
            "extra_info": null
        },
        {
            "layer_start": 7,
            "layer_end": 7,
            "partition": [
                [
                    0,
                    1,
                    2
                ],
                [
                    3
                ]
            ],
            "mapping_type": "telegate",
            "costs": {
                "num_comms": 0,
                "epairs": 0,
                "total_fidelity_loss": 0.0009490785341005846,
                "rgeo_mean_fid": 1.0,
                "execution_time": 0.0,
                "total_fidelity_log_sum": -0.000949198851153123,
                "total_fidelity": 0.9990512514955755,
                "remote_hops": 0,
                "remote_swaps": 0,
                "local_fidelity_loss": 0.0009490785341005846,
                "remote_fidelity_loss": 0.0,
                "local_fidelity_log_sum": -0.000949198851153123,
                "remote_fidelity_log_sum": 0.0,
                "local_fidelity": 0.9990512514955755,
                "remote_fidelity": 1.0,
                "local_gate_num": 4
            },
            "logical_phy_map": {
                "0": [
                    0,
                    1
                ],
                "1": [
                    0,
                    2
                ],
                "2": [
                    0,
                    0
                ],
                "3": [
                    1,
                    null
                ]
            },
            "extra_info": null
        },
        {
            "layer_start": 8,
            "layer_end": 8,
            "partition": [
                [
                    0,
                    1,
                    2
                ],
                [
                    3
                ]
            ],
            "mapping_type": "telegate",
            "costs": {
                "num_comms": 0,
                "epairs": 0,
                "total_fidelity_loss": 0.0,
                "rgeo_mean_fid": 1.0,
                "execution_time": 0.0,
                "total_fidelity_log_sum": 0.0,
                "total_fidelity": 1.0,
                "remote_hops": 0,
                "remote_swaps": 0,
                "local_fidelity_loss": 0.0,
                "remote_fidelity_loss": 0.0,
                "local_fidelity_log_sum": 0.0,
                "remote_fidelity_log_sum": 0.0,
                "local_fidelity": 1.0,
                "remote_fidelity": 1.0,
                "local_gate_num": 2
            },
            "logical_phy_map": {
                "0": [
                    0,
                    1
                ],
                "1": [
                    0,
                    2
                ],
                "2": [
                    0,
                    0
                ],
                "3": [
                    1,
                    null
                ]
            },
            "extra_info": null
        },
        {
            "layer_start": 9,
            "layer_end": 9,
            "partition": [
                [
                    0,
                    1,
                    2
                ],
                [
                    3
                ]
            ],
            "mapping_type": "telegate",
            "costs": {
                "num_comms": 1,
                "epairs": 1,
                "total_fidelity_loss": 0.07228652841594507,
                "rgeo_mean_fid": 0.93,
                "execution_time": 0.0,
                "total_fidelity_log_sum": -0.07485983934854362,
                "total_fidelity": 0.9278735285731711,
                "remote_hops": 1,
                "remote_swaps": 0,
                "local_fidelity_loss": 0.002286528415945122,
                "remote_fidelity_loss": 0.06999999999999995,
                "local_fidelity_log_sum": -0.0022891465137082428,
                "remote_fidelity_log_sum": -0.07257069283483537,
                "local_fidelity": 0.9977134715840549,
                "remote_fidelity": 0.93,
                "local_gate_num": 1
            },
            "logical_phy_map": {
                "0": [
                    0,
                    1
                ],
                "1": [
                    0,
                    2
                ],
                "2": [
                    0,
                    0
                ],
                "3": [
                    1,
                    null
                ]
            },
            "extra_info": null
        },
        {
            "layer_start": 10,
            "layer_end": 10,
            "partition": [
                [
                    0,
                    1,
                    2
                ],
                [
                    3
                ]
            ],
            "mapping_type": "telegate",
            "costs": {
                "num_comms": 0,
                "epairs": 0,
                "total_fidelity_loss": 0.0004108534720795142,
                "rgeo_mean_fid": 1.0,
                "execution_time": 0.0,
                "total_fidelity_log_sum": -0.0004108957958039796,
                "total_fidelity": 0.9995891886103124,
                "remote_hops": 0,
                "remote_swaps": 0,
                "local_fidelity_loss": 0.0004108534720795142,
                "remote_fidelity_loss": 0.0,
                "local_fidelity_log_sum": -0.0004108957958039796,
                "remote_fidelity_log_sum": 0.0,
                "local_fidelity": 0.9995891886103124,
                "remote_fidelity": 1.0,
                "local_gate_num": 4
            },
            "logical_phy_map": {
                "0": [
                    0,
                    1
                ],
                "1": [
                    0,
                    2
                ],
                "2": [
                    0,
                    0
                ],
                "3": [
                    1,
                    null
                ]
            },
            "extra_info": null
        },
        {
            "layer_start": 11,
            "layer_end": 11,
            "partition": [
                [
                    0,
                    1,
                    2
                ],
                [
                    3
                ]
            ],
            "mapping_type": "telegate",
            "costs": {
                "num_comms": 0,
                "epairs": 0,
                "total_fidelity_loss": 0.0005382250620210704,
                "rgeo_mean_fid": 1.0,
                "execution_time": 0.0,
                "total_fidelity_log_sum": -0.0005383030553491434,
                "total_fidelity": 0.9994618418037466,
                "remote_hops": 0,
                "remote_swaps": 0,
                "local_fidelity_loss": 0.0005382250620210704,
                "remote_fidelity_loss": 0.0,
                "local_fidelity_log_sum": -0.0005383030553491434,
                "remote_fidelity_log_sum": 0.0,
                "local_fidelity": 0.9994618418037466,
                "remote_fidelity": 1.0,
                "local_gate_num": 4
            },
            "logical_phy_map": {
                "0": [
                    0,
                    1
                ],
                "1": [
                    0,
                    2
                ],
                "2": [
                    0,
                    0
                ],
                "3": [
                    1,
                    null
                ]
            },
            "extra_info": null
        },
        {
            "layer_start": 12,
            "layer_end": 12,
            "partition": [
                [
                    0,
                    1,
                    2
                ],
                [
                    3
                ]
            ],
            "mapping_type": "telegate",
            "costs": {
                "num_comms": 0,
                "epairs": 0,
                "total_fidelity_loss": 0.023977371553112192,
                "rgeo_mean_fid": 1.0,
                "execution_time": 0.0,
                "total_fidelity_log_sum": -0.02404727570866196,
                "total_fidelity": 0.9762395562501023,
                "remote_hops": 0,
                "remote_swaps": 0,
                "local_fidelity_loss": 0.023977371553112192,
                "remote_fidelity_loss": 0.0,
                "local_fidelity_log_sum": -0.02404727570866196,
                "remote_fidelity_log_sum": 0.0,
                "local_fidelity": 0.9762395562501023,
                "remote_fidelity": 1.0,
                "local_gate_num": 12
            },
            "logical_phy_map": {
                "0": [
                    0,
                    1
                ],
                "1": [
                    0,
                    2
                ],
                "2": [
                    0,
                    0
                ],
                "3": [
                    1,
                    null
                ]
            },
            "extra_info": null
        },
        {
            "layer_start": 13,
            "layer_end": 13,
            "partition": [
                [
                    1,
                    2,
                    3
                ],
                [
                    0
                ]
            ],
            "mapping_type": "telegate",
            "costs": {
                "num_comms": 1,
                "epairs": 2,
                "total_fidelity_loss": 0.07269738188802459,
                "rgeo_mean_fid": 0.93,
                "execution_time": 0.0,
                "total_fidelity_log_sum": -0.0752707351443476,
                "total_fidelity": 0.9274923475594437,
                "remote_hops": 0,
                "remote_swaps": 1,
                "local_fidelity_loss": 0.0026973818880246365,
                "remote_fidelity_loss": 0.06999999999999995,
                "local_fidelity_log_sum": -0.0027000423095122224,
                "remote_fidelity_log_sum": -0.07257069283483537,
                "local_fidelity": 0.9973035995262834,
                "remote_fidelity": 0.93,
                "local_gate_num": 3
            },
            "logical_phy_map": {
                "0": [
                    1,
                    null
                ],
                "1": [
                    0,
                    2
                ],
                "2": [
                    0,
                    0
                ],
                "3": [
                    0,
                    1
                ]
            },
            "extra_info": null
        },
        {
            "layer_start": 14,
            "layer_end": 14,
            "partition": [
                [
                    1,
                    2,
                    3
                ],
                [
                    0
                ]
            ],
            "mapping_type": "telegate",
            "costs": {
                "num_comms": 0,
                "epairs": 0,
                "total_fidelity_loss": 0.0005382250620210704,
                "rgeo_mean_fid": 1.0,
                "execution_time": 0.0,
                "total_fidelity_log_sum": -0.0005383030553491434,
                "total_fidelity": 0.9994618418037466,
                "remote_hops": 0,
                "remote_swaps": 0,
                "local_fidelity_loss": 0.0005382250620210704,
                "remote_fidelity_loss": 0.0,
                "local_fidelity_log_sum": -0.0005383030553491434,
                "remote_fidelity_log_sum": 0.0,
                "local_fidelity": 0.9994618418037466,
                "remote_fidelity": 1.0,
                "local_gate_num": 3
            },
            "logical_phy_map": {
                "0": [
                    1,
                    null
                ],
                "1": [
                    0,
                    2
                ],
                "2": [
                    0,
                    0
                ],
                "3": [
                    0,
                    1
                ]
            },
            "extra_info": null
        },
        {
            "layer_start": 15,
            "layer_end": 15,
            "partition": [
                [
                    1,
                    2,
                    0
                ],
                [
                    3
                ]
            ],
            "mapping_type": "telegate",
            "costs": {
                "num_comms": 1,
                "epairs": 2,
                "total_fidelity_loss": 0.08514461371081798,
                "rgeo_mean_fid": 0.93,
                "execution_time": 0.0,
                "total_fidelity_log_sum": -0.0877457410522947,
                "total_fidelity": 0.915993746723577,
                "remote_hops": 0,
                "remote_swaps": 1,
                "local_fidelity_loss": 0.015144613710818027,
                "remote_fidelity_loss": 0.06999999999999995,
                "local_fidelity_log_sum": -0.015175048217459328,
                "remote_fidelity_log_sum": -0.07257069283483537,
                "local_fidelity": 0.9849395126059968,
                "remote_fidelity": 0.93,
                "local_gate_num": 11
            },
            "logical_phy_map": {
                "0": [
                    0,
                    1
                ],
                "1": [
                    0,
                    2
                ],
                "2": [
                    0,
                    0
                ],
                "3": [
                    1,
                    null
                ]
            },
            "extra_info": null
        },
        {
            "layer_start": 16,
            "layer_end": 16,
            "partition": [
                [
                    1,
                    2,
                    3
                ],
                [
                    0
                ]
            ],
            "mapping_type": "telegate",
            "costs": {
                "num_comms": 1,
                "epairs": 2,
                "total_fidelity_loss": 0.07269738188802459,
                "rgeo_mean_fid": 0.93,
                "execution_time": 0.0,
                "total_fidelity_log_sum": -0.0752707351443476,
                "total_fidelity": 0.9274923475594437,
                "remote_hops": 0,
                "remote_swaps": 1,
                "local_fidelity_loss": 0.0026973818880246365,
                "remote_fidelity_loss": 0.06999999999999995,
                "local_fidelity_log_sum": -0.0027000423095122224,
                "remote_fidelity_log_sum": -0.07257069283483537,
                "local_fidelity": 0.9973035995262834,
                "remote_fidelity": 0.93,
                "local_gate_num": 3
            },
            "logical_phy_map": {
                "0": [
                    1,
                    null
                ],
                "1": [
                    0,
                    2
                ],
                "2": [
                    0,
                    0
                ],
                "3": [
                    0,
                    1
                ]
            },
            "extra_info": null
        },
        {
            "layer_start": 17,
            "layer_end": 17,
            "partition": [
                [
                    1,
                    2,
                    3
                ],
                [
                    0
                ]
            ],
            "mapping_type": "telegate",
            "costs": {
                "num_comms": 0,
                "epairs": 0,
                "total_fidelity_loss": 0.0005382250620210704,
                "rgeo_mean_fid": 1.0,
                "execution_time": 0.0,
                "total_fidelity_log_sum": -0.0005383030553491434,
                "total_fidelity": 0.9994618418037466,
                "remote_hops": 0,
                "remote_swaps": 0,
                "local_fidelity_loss": 0.0005382250620210704,
                "remote_fidelity_loss": 0.0,
                "local_fidelity_log_sum": -0.0005383030553491434,
                "remote_fidelity_log_sum": 0.0,
                "local_fidelity": 0.9994618418037466,
                "remote_fidelity": 1.0,
                "local_gate_num": 3
            },
            "logical_phy_map": {
                "0": [
                    1,
                    null
                ],
                "1": [
                    0,
                    2
                ],
                "2": [
                    0,
                    0
                ],
                "3": [
                    0,
                    1
                ]
            },
            "extra_info": null
        },
        {
            "layer_start": 18,
            "layer_end": 18,
            "partition": [
                [
                    1,
                    2,
                    0
                ],
                [
                    3
                ]
            ],
            "mapping_type": "telegate",
            "costs": {
                "num_comms": 1,
                "epairs": 2,
                "total_fidelity_loss": 0.09397737155311214,
                "rgeo_mean_fid": 0.93,
                "execution_time": 0.0,
                "total_fidelity_log_sum": -0.09661796854349733,
                "total_fidelity": 0.9079027873125952,
                "remote_hops": 0,
                "remote_swaps": 1,
                "local_fidelity_loss": 0.023977371553112192,
                "remote_fidelity_loss": 0.06999999999999995,
                "local_fidelity_log_sum": -0.02404727570866196,
                "remote_fidelity_log_sum": -0.07257069283483537,
                "local_fidelity": 0.9762395562501023,
                "remote_fidelity": 0.93,
                "local_gate_num": 11
            },
            "logical_phy_map": {
                "0": [
                    0,
                    1
                ],
                "1": [
                    0,
                    2
                ],
                "2": [
                    0,
                    0
                ],
                "3": [
                    1,
                    null
                ]
            },
            "extra_info": null
        },
        {
            "layer_start": 19,
            "layer_end": 19,
            "partition": [
                [
                    1,
                    2,
                    3
                ],
                [
                    0
                ]
            ],
            "mapping_type": "telegate",
            "costs": {
                "num_comms": 1,
                "epairs": 2,
                "total_fidelity_loss": 0.07248110379859392,
                "rgeo_mean_fid": 0.93,
                "execution_time": 0.0,
                "total_fidelity_log_sum": -0.07505443366343814,
                "total_fidelity": 0.9276929872262992,
                "remote_hops": 0,
                "remote_swaps": 1,
                "local_fidelity_loss": 0.002481103798593961,
                "remote_fidelity_loss": 0.06999999999999995,
                "local_fidelity_log_sum": -0.0024837408286027688,
                "remote_fidelity_log_sum": -0.07257069283483537,
                "local_fidelity": 0.9975193411035475,
                "remote_fidelity": 0.93,
                "local_gate_num": 3
            },
            "logical_phy_map": {
                "0": [
                    1,
                    null
                ],
                "1": [
                    0,
                    2
                ],
                "2": [
                    0,
                    0
                ],
                "3": [
                    0,
                    1
                ]
            },
            "extra_info": null
        },
        {
            "layer_start": 20,
            "layer_end": 20,
            "partition": [
                [
                    1,
                    2,
                    3
                ],
                [
                    0
                ]
            ],
            "mapping_type": "telegate",
            "costs": {
                "num_comms": 0,
                "epairs": 0,
                "total_fidelity_loss": 0.0005599277688029065,
                "rgeo_mean_fid": 1.0,
                "execution_time": 0.0,
                "total_fidelity_log_sum": -0.0005600102213640708,
                "total_fidelity": 0.9994401465550931,
                "remote_hops": 0,
                "remote_swaps": 0,
                "local_fidelity_loss": 0.0005599277688029065,
                "remote_fidelity_loss": 0.0,
                "local_fidelity_log_sum": -0.0005600102213640708,
                "remote_fidelity_log_sum": 0.0,
                "local_fidelity": 0.9994401465550931,
                "remote_fidelity": 1.0,
                "local_gate_num": 4
            },
            "logical_phy_map": {
                "0": [
                    1,
                    null
                ],
                "1": [
                    0,
                    2
                ],
                "2": [
                    0,
                    0
                ],
                "3": [
                    0,
                    1
                ]
            },
            "extra_info": null
        },
        {
            "layer_start": 21,
            "layer_end": 21,
            "partition": [
                [
                    1,
                    2,
                    3
                ],
                [
                    0
                ]
            ],
            "mapping_type": "telegate",
            "costs": {
                "num_comms": 0,
                "epairs": 0,
                "total_fidelity_loss": 0.000194575382648839,
                "rgeo_mean_fid": 1.0,
                "execution_time": 0.0,
                "total_fidelity_log_sum": -0.00019459431489452612,
                "total_fidelity": 0.9998054246173511,
                "remote_hops": 0,
                "remote_swaps": 0,
                "local_fidelity_loss": 0.000194575382648839,
                "remote_fidelity_loss": 0.0,
                "local_fidelity_log_sum": -0.00019459431489452612,
                "remote_fidelity_log_sum": 0.0,
                "local_fidelity": 0.9998054246173511,
                "remote_fidelity": 1.0,
                "local_gate_num": 3
            },
            "logical_phy_map": {
                "0": [
                    1,
                    null
                ],
                "1": [
                    0,
                    2
                ],
                "2": [
                    0,
                    0
                ],
                "3": [
                    0,
                    1
                ]
            },
            "extra_info": null
        },
        {
            "layer_start": 22,
            "layer_end": 22,
            "partition": [
                [
                    1,
                    2,
                    3
                ],
                [
                    0
                ]
            ],
            "mapping_type": "telegate",
            "costs": {
                "num_comms": 0,
                "epairs": 0,
                "total_fidelity_loss": 0.00667035327691945,
                "rgeo_mean_fid": 1.0,
                "execution_time": 0.0,
                "total_fidelity_log_sum": -0.006692699510287167,
                "total_fidelity": 0.9933296467230806,
                "remote_hops": 0,
                "remote_swaps": 0,
                "local_fidelity_loss": 0.00667035327691945,
                "remote_fidelity_loss": 0.0,
                "local_fidelity_log_sum": -0.006692699510287167,
                "remote_fidelity_log_sum": 0.0,
                "local_fidelity": 0.9933296467230806,
                "remote_fidelity": 1.0,
                "local_gate_num": 2
            },
            "logical_phy_map": {
                "0": [
                    1,
                    null
                ],
                "1": [
                    0,
                    2
                ],
                "2": [
                    0,
                    0
                ],
                "3": [
                    0,
                    1
                ]
            },
            "extra_info": null
        },
        {
            "layer_start": 23,
            "layer_end": 23,
            "partition": [
                [
                    2,
                    3,
                    0
                ],
                [
                    1
                ]
            ],
            "mapping_type": "telegate",
            "costs": {
                "num_comms": 1,
                "epairs": 2,
                "total_fidelity_loss": 0.09417194693576098,
                "rgeo_mean_fid": 0.93,
                "execution_time": 0.0,
                "total_fidelity_log_sum": -0.09681256285839186,
                "total_fidelity": 0.9077261317803458,
                "remote_hops": 0,
                "remote_swaps": 1,
                "local_fidelity_loss": 0.02417194693576103,
                "remote_fidelity_loss": 0.06999999999999995,
                "local_fidelity_log_sum": -0.024241870023556485,
                "remote_fidelity_log_sum": -0.07257069283483537,
                "local_fidelity": 0.9760496040648879,
                "remote_fidelity": 0.93,
                "local_gate_num": 11
            },
            "logical_phy_map": {
                "0": [
                    0,
                    2
                ],
                "1": [
                    1,
                    null
                ],
                "2": [
                    0,
                    0
                ],
                "3": [
                    0,
                    1
                ]
            },
            "extra_info": null
        },
        {
            "layer_start": 24,
            "layer_end": 24,
            "partition": [
                [
                    2,
                    3,
                    0
                ],
                [
                    1
                ]
            ],
            "mapping_type": "telegate",
            "costs": {
                "num_comms": 0,
                "epairs": 0,
                "total_fidelity_loss": 0.0004108534720795142,
                "rgeo_mean_fid": 1.0,
                "execution_time": 0.0,
                "total_fidelity_log_sum": -0.0004108957958039796,
                "total_fidelity": 0.9995891886103124,
                "remote_hops": 0,
                "remote_swaps": 0,
                "local_fidelity_loss": 0.0004108534720795142,
                "remote_fidelity_loss": 0.0,
                "local_fidelity_log_sum": -0.0004108957958039796,
                "remote_fidelity_log_sum": 0.0,
                "local_fidelity": 0.9995891886103124,
                "remote_fidelity": 1.0,
                "local_gate_num": 3
            },
            "logical_phy_map": {
                "0": [
                    0,
                    2
                ],
                "1": [
                    1,
                    null
                ],
                "2": [
                    0,
                    0
                ],
                "3": [
                    0,
                    1
                ]
            },
            "extra_info": null
        },
        {
            "layer_start": 25,
            "layer_end": 25,
            "partition": [
                [
                    2,
                    3,
                    1
                ],
                [
                    0
                ]
            ],
            "mapping_type": "telegate",
            "costs": {
                "num_comms": 1,
                "epairs": 2,
                "total_fidelity_loss": 0.0766703532769194,
                "rgeo_mean_fid": 0.93,
                "execution_time": 0.0,
                "total_fidelity_log_sum": -0.07926339234512254,
                "total_fidelity": 0.923796571452465,
                "remote_hops": 0,
                "remote_swaps": 1,
                "local_fidelity_loss": 0.00667035327691945,
                "remote_fidelity_loss": 0.06999999999999995,
                "local_fidelity_log_sum": -0.006692699510287167,
                "remote_fidelity_log_sum": -0.07257069283483537,
                "local_fidelity": 0.9933296467230806,
                "remote_fidelity": 0.93,
                "local_gate_num": 2
            },
            "logical_phy_map": {
                "0": [
                    1,
                    null
                ],
                "1": [
                    0,
                    2
                ],
                "2": [
                    0,
                    0
                ],
                "3": [
                    0,
                    1
                ]
            },
            "extra_info": null
        },
        {
            "layer_start": 26,
            "layer_end": 26,
            "partition": [
                [
                    2,
                    3,
                    0
                ],
                [
                    1
                ]
            ],
            "mapping_type": "telegate",
            "costs": {
                "num_comms": 1,
                "epairs": 2,
                "total_fidelity_loss": 0.08533918909346681,
                "rgeo_mean_fid": 0.93,
                "execution_time": 0.0,
                "total_fidelity_log_sum": -0.08794033536718923,
                "total_fidelity": 0.9158155168898043,
                "remote_hops": 0,
                "remote_swaps": 1,
                "local_fidelity_loss": 0.015339189093466866,
                "remote_fidelity_loss": 0.06999999999999995,
                "local_fidelity_log_sum": -0.015369642532353855,
                "remote_fidelity_log_sum": -0.07257069283483537,
                "local_fidelity": 0.9847478676234455,
                "remote_fidelity": 0.93,
                "local_gate_num": 11
            },
            "logical_phy_map": {
                "0": [
                    0,
                    2
                ],
                "1": [
                    1,
                    null
                ],
                "2": [
                    0,
                    0
                ],
                "3": [
                    0,
                    1
                ]
            },
            "extra_info": null
        },
        {
            "layer_start": 27,
            "layer_end": 27,
            "partition": [
                [
                    2,
                    3,
                    0
                ],
                [
                    1
                ]
            ],
            "mapping_type": "telegate",
            "costs": {
                "num_comms": 0,
                "epairs": 0,
                "total_fidelity_loss": 0.0004108534720795142,
                "rgeo_mean_fid": 1.0,
                "execution_time": 0.0,
                "total_fidelity_log_sum": -0.0004108957958039796,
                "total_fidelity": 0.9995891886103124,
                "remote_hops": 0,
                "remote_swaps": 0,
                "local_fidelity_loss": 0.0004108534720795142,
                "remote_fidelity_loss": 0.0,
                "local_fidelity_log_sum": -0.0004108957958039796,
                "remote_fidelity_log_sum": 0.0,
                "local_fidelity": 0.9995891886103124,
                "remote_fidelity": 1.0,
                "local_gate_num": 3
            },
            "logical_phy_map": {
                "0": [
                    0,
                    2
                ],
                "1": [
                    1,
                    null
                ],
                "2": [
                    0,
                    0
                ],
                "3": [
                    0,
                    1
                ]
            },
            "extra_info": null
        },
        {
            "layer_start": 28,
            "layer_end": 28,
            "partition": [
                [
                    2,
                    3,
                    1
                ],
                [
                    0
                ]
            ],
            "mapping_type": "telegate",
            "costs": {
                "num_comms": 1,
                "epairs": 2,
                "total_fidelity_loss": 0.0766703532769194,
                "rgeo_mean_fid": 0.93,
                "execution_time": 0.0,
                "total_fidelity_log_sum": -0.07926339234512254,
                "total_fidelity": 0.923796571452465,
                "remote_hops": 0,
                "remote_swaps": 1,
                "local_fidelity_loss": 0.00667035327691945,
                "remote_fidelity_loss": 0.06999999999999995,
                "local_fidelity_log_sum": -0.006692699510287167,
                "remote_fidelity_log_sum": -0.07257069283483537,
                "local_fidelity": 0.9933296467230806,
                "remote_fidelity": 0.93,
                "local_gate_num": 2
            },
            "logical_phy_map": {
                "0": [
                    1,
                    null
                ],
                "1": [
                    0,
                    2
                ],
                "2": [
                    0,
                    0
                ],
                "3": [
                    0,
                    1
                ]
            },
            "extra_info": null
        },
        {
            "layer_start": 29,
            "layer_end": 29,
            "partition": [
                [
                    2,
                    3,
                    0
                ],
                [
                    1
                ]
            ],
            "mapping_type": "telegate",
            "costs": {
                "num_comms": 1,
                "epairs": 2,
                "total_fidelity_loss": 0.09417194693576098,
                "rgeo_mean_fid": 0.93,
                "execution_time": 0.0,
                "total_fidelity_log_sum": -0.09681256285839186,
                "total_fidelity": 0.9077261317803458,
                "remote_hops": 0,
                "remote_swaps": 1,
                "local_fidelity_loss": 0.02417194693576103,
                "remote_fidelity_loss": 0.06999999999999995,
                "local_fidelity_log_sum": -0.024241870023556485,
                "remote_fidelity_log_sum": -0.07257069283483537,
                "local_fidelity": 0.9760496040648879,
                "remote_fidelity": 0.93,
                "local_gate_num": 12
            },
            "logical_phy_map": {
                "0": [
                    0,
                    2
                ],
                "1": [
                    1,
                    null
                ],
                "2": [
                    0,
                    0
                ],
                "3": [
                    0,
                    1
                ]
            },
            "extra_info": null
        },
        {
            "layer_start": 30,
            "layer_end": 30,
            "partition": [
                [
                    2,
                    3,
                    0
                ],
                [
                    1
                ]
            ],
            "mapping_type": "telegate",
            "costs": {
                "num_comms": 0,
                "epairs": 0,
                "total_fidelity_loss": 0.0005599277688029065,
                "rgeo_mean_fid": 1.0,
                "execution_time": 0.0,
                "total_fidelity_log_sum": -0.0005600102213640708,
                "total_fidelity": 0.9994401465550931,
                "remote_hops": 0,
                "remote_swaps": 0,
                "local_fidelity_loss": 0.0005599277688029065,
                "remote_fidelity_loss": 0.0,
                "local_fidelity_log_sum": -0.0005600102213640708,
                "remote_fidelity_log_sum": 0.0,
                "local_fidelity": 0.9994401465550931,
                "remote_fidelity": 1.0,
                "local_gate_num": 4
            },
            "logical_phy_map": {
                "0": [
                    0,
                    2
                ],
                "1": [
                    1,
                    null
                ],
                "2": [
                    0,
                    0
                ],
                "3": [
                    0,
                    1
                ]
            },
            "extra_info": null
        },
        {
            "layer_start": 31,
            "layer_end": 31,
            "partition": [
                [
                    2,
                    3,
                    0
                ],
                [
                    1
                ]
            ],
            "mapping_type": "telegate",
            "costs": {
                "num_comms": 0,
                "epairs": 0,
                "total_fidelity_loss": 0.000194575382648839,
                "rgeo_mean_fid": 1.0,
                "execution_time": 0.0,
                "total_fidelity_log_sum": -0.00019459431489452612,
                "total_fidelity": 0.9998054246173511,
                "remote_hops": 0,
                "remote_swaps": 0,
                "local_fidelity_loss": 0.000194575382648839,
                "remote_fidelity_loss": 0.0,
                "local_fidelity_log_sum": -0.00019459431489452612,
                "remote_fidelity_log_sum": 0.0,
                "local_fidelity": 0.9998054246173511,
                "remote_fidelity": 1.0,
                "local_gate_num": 3
            },
            "logical_phy_map": {
                "0": [
                    0,
                    2
                ],
                "1": [
                    1,
                    null
                ],
                "2": [
                    0,
                    0
                ],
                "3": [
                    0,
                    1
                ]
            },
            "extra_info": null
        },
        {
            "layer_start": 32,
            "layer_end": 32,
            "partition": [
                [
                    2,
                    3,
                    0
                ],
                [
                    1
                ]
            ],
            "mapping_type": "telegate",
            "costs": {
                "num_comms": 0,
                "epairs": 0,
                "total_fidelity_loss": 0.0,
                "rgeo_mean_fid": 1.0,
                "execution_time": 0.0,
                "total_fidelity_log_sum": 0.0,
                "total_fidelity": 1.0,
                "remote_hops": 0,
                "remote_swaps": 0,
                "local_fidelity_loss": 0.0,
                "remote_fidelity_loss": 0.0,
                "local_fidelity_log_sum": 0.0,
                "remote_fidelity_log_sum": 0.0,
                "local_fidelity": 1.0,
                "remote_fidelity": 1.0,
                "local_gate_num": 1
            },
            "logical_phy_map": {
                "0": [
                    0,
                    2
                ],
                "1": [
                    1,
                    null
                ],
                "2": [
                    0,
                    0
                ],
                "3": [
                    0,
                    1
                ]
            },
            "extra_info": null
        }
    ]
}